paifulogger/__init__.py
paifulogger/__main__.py
paifulogger/config.py
paifulogger/log.py
paifulogger/paifu_dl.py
paifulogger/version.py
paifulogger/i18n/__init__.py
paifulogger/i18n/i18n.py
paifulogger/i18n/i18n.pyi
paifulogger/localizations/en.json
paifulogger/localizations/ja.json
paifulogger/localizations/zh.json
paifulogger/localizations/zh_tw.json
paifulogger/logfile/__init__.py
paifulogger/logfile/log_into_csv.py
paifulogger/logfile/log_into_html.py
paifulogger/logfile/log_into_template.py
paifulogger/logfile/log_into_xlsx.py
paifulogger/mjlog2mjai/parse.py
paifulogger/mjlog2mjai/test.py
paifulogger/paifu/__init__.py
paifulogger/paifu/paifu.py
paifulogger/paifu/paifu.pyi
paifulogger/utils/__init__.py
paifulogger/utils/get_paifu.py
paifulogger/utils/url_log.py
pub_tools/pub.py
test/__init__.py
test/test.py
PaifuLogger-0.4.2.dist-info/LICENSE
PaifuLogger-0.4.2.dist-info/METADATA
PaifuLogger-0.4.2.dist-info/WHEEL
PaifuLogger-0.4.2.dist-info/entry_points.txt
PaifuLogger-0.4.2.dist-info/top_level.txt
PaifuLogger-0.4.2.dist-info/RECORD
